dvc_s3/__init__.py
dvc_s3/_dvc_s3_version.py
dvc_s3/tests/__init__.py
dvc_s3/tests/benchmarks.py
dvc_s3/tests/cloud.py
dvc_s3/tests/conftest.py
dvc_s3/tests/fixtures.py
dvc_s3/tests/test_dvc.py
dvc_s3/tests/test_s3.py
dvc_s3/tests/test_utils.py
dvc_s3-3.2.1.dist-info/licenses/LICENSE
dvc_s3-3.2.1.dist-info/METADATA
dvc_s3-3.2.1.dist-info/WHEEL
dvc_s3-3.2.1.dist-info/top_level.txt
dvc_s3-3.2.1.dist-info/RECORD
